README.md
setup.py
media_platform/__init__.py
media_platform/error_code.py
media_platform/media_platform_client.py
media_platform/auth/__init__.py
media_platform/auth/app_authenticator.py
media_platform/auth/jwt_coder.py
media_platform/auth/token.py
media_platform/exception/__init__.py
media_platform/exception/bad_gateway_exception.py
media_platform/exception/conflict_exception.py
media_platform/exception/forbidden_exception.py
media_platform/exception/media_platform_exception.py
media_platform/exception/not_found_exception.py
media_platform/exception/server_error_exception.py
media_platform/exception/unauthorized_exception.py
media_platform/exception/unsupported_media_exception.py
media_platform/http_client/__init__.py
media_platform/http_client/authenticated_http_client.py
media_platform/http_client/response_processor.py
media_platform/job/__init__.py
media_platform/job/convert_font_job.py
media_platform/job/convert_font_job_group.py
media_platform/job/create_archive_job.py
media_platform/job/extract_poster_job.py
media_platform/job/extract_poster_job_group.py
media_platform/job/extract_storyboard_job.py
media_platform/job/extract_storyboard_job_group.py
media_platform/job/image_operation_job.py
media_platform/job/import_file_job.py
media_platform/job/index_image_job.py
media_platform/job/job.py
media_platform/job/job_callback_payload.py
media_platform/job/job_deserializer.py
media_platform/job/job_group.py
media_platform/job/job_type.py
media_platform/job/replace_extra_metadata_job.py
media_platform/job/scan_file_job.py
media_platform/job/scan_file_job_group.py
media_platform/job/specification.py
media_platform/job/subset_font_job.py
media_platform/job/subset_font_job_group.py
media_platform/job/transcode_job.py
media_platform/job/transcode_job_group.py
media_platform/job/extract_archive/__init__.py
media_platform/job/extract_archive/extract_archive_job.py
media_platform/job/extract_archive/extraction_report.py
media_platform/job/result/__init__.py
wix_media_platform.egg-info/PKG-INFO
wix_media_platform.egg-info/SOURCES.txt
wix_media_platform.egg-info/dependency_links.txt
wix_media_platform.egg-info/requires.txt
wix_media_platform.egg-info/top_level.txt