Metadata-Version: 1.1
Name: wix-media-platform
Version: 1.71.0
Summary: Wix Media Platform python SDK
Home-page: https://github.com/wix/media-platform-python-sdk
Author: Wix Media Platform
Author-email: mcloud@wix.com
License: UNKNOWN
Platform: UNKNOWN
Classifier: Development Status :: 5 - Production/Stable
Classifier: Intended Audience :: Developers
Classifier: Natural Language :: English
Classifier: Programming Language :: Python
Classifier: Programming Language :: Python :: 3.7
Classifier: Programming Language :: Python :: 3.8
